ccc/__init__.py
ccc/calcfunctions.py
ccc/calculator.py
ccc/ccc_asset_data.csv
ccc/constants.py
ccc/controls_callback_script.py
ccc/data.py
ccc/default_parameters.json
ccc/get_taxcalc_rates.py
ccc/parameters.py
ccc/paramfunctions.py
ccc/records_variables.json
ccc/styles.py
ccc/tax_depreciation_rules.json
ccc/utils.py
cost_of_capital_calculator-2.0.0.dist-info/LICENSE
cost_of_capital_calculator-2.0.0.dist-info/METADATA
cost_of_capital_calculator-2.0.0.dist-info/WHEEL
cost_of_capital_calculator-2.0.0.dist-info/top_level.txt
cost_of_capital_calculator-2.0.0.dist-info/RECORD
