Metadata-Version: 2.1
Name: cost-of-capital-calculator
Version: 2.0.0
Summary: CCC: A Cost of Capital Calculator
Home-page: https://github.com/PSLmodels/Cost-of-Capital-Calculator
Download-URL: https://github.com/PSLmodels/Cost-of-Capital-Calculator
License: CC0 1.0 Universal (CC0 1.0) Public Domain Dedication
Classifier: Development Status :: 4 - Beta
Classifier: Intended Audience :: Developers
Classifier: Natural Language :: English
Classifier: License :: CC0 1.0 Universal (CC0 1.0) Public Domain Dedication
Classifier: Operating System :: OS Independent
Classifier: Programming Language :: Python
Classifier: Programming Language :: Python :: 3
Classifier: Programming Language :: Python :: 3.10
Classifier: Programming Language :: Python :: 3.11
Classifier: Programming Language :: Python :: 3.12
Classifier: Topic :: Software Development :: Libraries :: Python Modules
License-File: LICENSE
Requires-Dist: taxcalc
Requires-Dist: pandas
Requires-Dist: bokeh
Requires-Dist: numpy
Requires-Dist: paramtools
